codingcalc/__init__.py
codingcalc-0.1.dist-info/LICENSE.txt
codingcalc-0.1.dist-info/METADATA
codingcalc-0.1.dist-info/WHEEL
codingcalc-0.1.dist-info/top_level.txt
codingcalc-0.1.dist-info/RECORD
