Metadata-Version: 2.1
Name: codingcalc
Version: 0.1
Summary: Calculator for more than 2 numbers
Home-page: UNKNOWN
Author: Sameer Lalchandani
Author-email: sameer.lalchandani2022@vitstudent.ac.in
License: UNKNOWN
Platform: UNKNOWN
Classifier: Programming Language :: Python :: 3
Classifier: License :: OSI Approved :: MIT License
Classifier: Operating System :: OS Independent
License-File: LICENSE.txt
